doc/source/conf.py
examples/standard/plot_em.py
examples/standard/plot_filter.py
examples/standard/plot_missing.py
examples/standard/plot_online.py
examples/standard/plot_sin.py
examples/unscented/plot_additive.py
examples/unscented/plot_filter.py
pykalman/__init__.py
pykalman/standard.py
pykalman/unscented.py
pykalman/utils.py
pykalman/datasets/__init__.py
pykalman/datasets/base.py
pykalman/datasets/data/robot.mat
pykalman/datasets/descr/robot.rst
pykalman/sqrt/__init__.py
pykalman/sqrt/bierman.py
pykalman/sqrt/cholesky.py
pykalman/sqrt/unscented.py
pykalman_bardo-0.9.7.dist-info/COPYING
pykalman_bardo-0.9.7.dist-info/METADATA
pykalman_bardo-0.9.7.dist-info/WHEEL
pykalman_bardo-0.9.7.dist-info/top_level.txt
pykalman_bardo-0.9.7.dist-info/zip-safe
pykalman_bardo-0.9.7.dist-info/RECORD
