Metadata-Version: 2.1
Name: pykalman-bardo
Version: 0.9.7
Summary: An implementation of the Kalman Filter, Kalman Smoother, and EM algorithm in Python
Author-email: Daniel Duckworth <pykalman@gmail.com>, Maksym Balatsko <mbalatsko@gmail.com>
License: All code contained except that in pykalman/utils.py is released under the
Project-URL: Homepage, https://github.com/pybardo/pykalman
Project-URL: Repository, https://github.com/pybardo/pykalman
Project-URL: Documentation, https://pykalman.github.io/
Keywords: kalman filter,smoothing
Classifier: Development Status :: 4 - Beta
Classifier: Intended Audience :: Science/Research
Classifier: License :: OSI Approved :: BSD License
Classifier: Operating System :: OS Independent
Classifier: Programming Language :: Python
Classifier: Programming Language :: Python :: 3
Classifier: Topic :: Scientific/Engineering :: Artificial Intelligence
Requires-Python: >=3.6
License-File: COPYING
Requires-Dist: numpy
Requires-Dist: scipy
Provides-Extra: all
Requires-Dist: pytest ; extra == 'all'
Requires-Dist: Sphinx ; extra == 'all'
Requires-Dist: numpydoc ; extra == 'all'
Requires-Dist: twine ; extra == 'all'
Provides-Extra: docs
Requires-Dist: Sphinx ; extra == 'docs'
Requires-Dist: numpydoc ; extra == 'docs'
Provides-Extra: tests
Requires-Dist: pytest ; extra == 'tests'
